README.rst
setup.cfg
setup.py
awvspy/__init__.py
awvspy/api.py
awvspy/exceptions.py
awvspy/models.py
awvspy/status_codes.py
awvspy/utils.py
awvspy.egg-info/PKG-INFO
awvspy.egg-info/SOURCES.txt
awvspy.egg-info/dependency_links.txt
awvspy.egg-info/not-zip-safe
awvspy.egg-info/top_level.txt